pubfisher/__init__.py
pubfisher/annotate.py
pubfisher/core.py
pubfisher/gi_composites.py
pubfisher/fishers/__init__.py
pubfisher/fishers/googlescholar.py
pubfisher/fishers/share.py
pubfisher-2019.11.dist-info/LICENSE
pubfisher-2019.11.dist-info/METADATA
pubfisher-2019.11.dist-info/WHEEL
pubfisher-2019.11.dist-info/top_level.txt
pubfisher-2019.11.dist-info/RECORD
