Metadata-Version: 2.1
Name: pubfisher
Version: 2019.11
Summary: Query information about scientific publications on the web.
Home-page: https://github.com/momits/pubfisher/
Author: Moritz Renftle
Author-email: pubfisher@momits.de
License: UNKNOWN
Platform: UNKNOWN
Classifier: Programming Language :: Python :: 3
Classifier: License :: OSI Approved :: MIT License
Classifier: Operating System :: OS Independent
Requires-Python: >=3.6
Requires-Dist: pycairo
Requires-Dist: PyGObject
Requires-Dist: beautifulsoup4
Requires-Dist: bibtexparser
Requires-Dist: requests
Requires-Dist: typeguard
